marketclock/__init__.py
worldtradeclock_feizi_asp-0.1.2.dist-info/licenses/LICENSE
worldtradeclock_feizi_asp-0.1.2.dist-info/METADATA
worldtradeclock_feizi_asp-0.1.2.dist-info/WHEEL
worldtradeclock_feizi_asp-0.1.2.dist-info/top_level.txt
worldtradeclock_feizi_asp-0.1.2.dist-info/RECORD
