Metadata-Version: 2.4
Name: worldtradeclock-feizi-asp
Version: 0.1.2
Summary: World financial market open/close & volume tracker
Author: Prof.Dr Feizi & Ahad Esmaeilzadeh
Author-email: Taimaz <your@email.com>
License: MIT License
Requires-Python: >=3.7
License-File: LICENSE
Requires-Dist: pytz
Requires-Dist: pandas
Requires-Dist: requests
Requires-Dist: arabic-reshaper
Requires-Dist: python-bidi
Dynamic: author
Dynamic: license-file
